Metadata-Version: 2.1
Name: unrest-schema
Version: 0.1.1
Summary: Convert Django forms into json schema
Home-page: https://github.com/chriscauley/unrest-schema
Author: Chris Cauley
Author-email: chris@lablackey.com
License: MIT
Keywords: utils,django
Platform: UNKNOWN
